pietorch/__init__.py
pietorch/cached_poisson_blender.py
pietorch/functional.py
pietorch/functional_numpy.py
pietorch/utils.py
pie_torch-0.0.1.dist-info/LICENSE
pie_torch-0.0.1.dist-info/METADATA
pie_torch-0.0.1.dist-info/WHEEL
pie_torch-0.0.1.dist-info/top_level.txt
pie_torch-0.0.1.dist-info/RECORD
