Metadata-Version: 2.1
Name: pie-torch
Version: 0.0.1
Summary: N-dimensional Poisson image editing implemented with Pytorch and NumPy
Home-page: https://github.com/matt-baugh/pytorch-poisson-image-editing
Author: Matthew Baugh
Author-email: Matthew Baugh <matthew.baugh17@imperial.ac.uk>
Project-URL: Homepage, https://github.com/matt-baugh/pytorch-poisson-image-editing
Classifier: Programming Language :: Python :: 3
Classifier: Operating System :: OS Independent
Requires-Python: >=3.8
License-File: LICENSE
Requires-Dist: torch (>=1.7)
Requires-Dist: scipy (>=1.4)
Requires-Dist: numpy
